java_dependency_viewer/__init__.py
java_dependency_viewer/analyzer.py
java_dependency_viewer/cli.py
java_dependency_viewer/graph.py
java_dependency_viewer/renderer.py
java_dependency_viewer/templates/cytoscape_template.html
java_dependency_viewer/templates/sigma_template.html
java_dependency_viewer/templates/vis_template.html
tests/__init__.py
tests/test_analyzer.py
tests/test_graph.py
java_dependency_viewer-0.1.0.dist-info/METADATA
java_dependency_viewer-0.1.0.dist-info/WHEEL
java_dependency_viewer-0.1.0.dist-info/entry_points.txt
java_dependency_viewer-0.1.0.dist-info/top_level.txt
java_dependency_viewer-0.1.0.dist-info/RECORD
