Metadata-Version: 2.1
Name: java-dependency-viewer
Version: 0.1.0
Summary: A CLI tool for analyzing Java class dependencies using javap.
Home-page: https://github.com/payashi/java-dependency-viewer
Author: Hiromichi Hayashi
Author-email: 6phyphy6@gmail.com
License: MIT
Classifier: Programming Language :: Python :: 3
Classifier: License :: OSI Approved :: MIT License
Classifier: Operating System :: OS Independent
Requires-Python: >=3.6
Requires-Dist: networkx>=2.5
